setup.py
approxngd/__init__.py
approxngd/kfac_optimizer.py
approxngd.egg-info/PKG-INFO
approxngd.egg-info/SOURCES.txt
approxngd.egg-info/dependency_links.txt
approxngd.egg-info/top_level.txt
approxngd/layers/__init__.py
approxngd/layers/conv_block.py
approxngd/layers/fisher_block.py
approxngd/layers/identity.py
approxngd/layers/linear_block.py
approxngd/layers/utils.py
approxngd/utils/__init__.py
approxngd/utils/context_variable.py
approxngd/utils/lock.py
approxngd/utils/moving_average.py
approxngd/utils/utils.py