Metadata-Version: 2.1
Name: approxngd
Version: 0.1.1
Summary: This package provides an pip installable way to implement KFAC as created by Nicholas Gao and previously by Marten et al.
Author: Ragha Rao
Author-email: ragharao2001@gmail.com
Classifier: Programming Language :: Python :: 3
Classifier: Operating System :: OS Independent
Requires-Python: >=3.7
